skylab2iai/__init__.py
skylab2iai/catalog/__init__.py
skylab2iai/catalog/catalog.py
skylab2iai/storage/__init__.py
skylab2iai/storage/plate.py
skylab2iai/storage/plate_frame.py
skylab2iai/storage/skylab-data.db
skylab2iai/storage/sql_connection.py
skylab2iai-0.0.10.dist-info/licenses/LICENSE
skylab2iai-0.0.10.dist-info/METADATA
skylab2iai-0.0.10.dist-info/WHEEL
skylab2iai-0.0.10.dist-info/top_level.txt
skylab2iai-0.0.10.dist-info/RECORD
