Metadata-Version: 2.4
Name: skylab2iai
Version: 0.0.10
Summary: A Python library for accessing and analyzing Skylab mission data
Author-email: Tiago Ferrer <ferrertiago@gmail.com>
Project-URL: Homepage, https://github.com/tferrer/skylab2iai
Project-URL: Repository, https://github.com/tferrer/skylab2iai
Classifier: Programming Language :: Python :: 3
Classifier: License :: OSI Approved :: MIT License
Classifier: Operating System :: OS Independent
Requires-Python: >=3.10
License-File: LICENSE
Requires-Dist: pandas>=2.0.0
Requires-Dist: requests>=2.31.0
Provides-Extra: dev
Requires-Dist: pytest>=7.0.0; extra == "dev"
Requires-Dist: pytest-cov>=4.0.0; extra == "dev"
Requires-Dist: pytest-mock>=3.10.0; extra == "dev"
Dynamic: license-file
